richset/__init__.py
richset/_version.py
richset/comparable.py
richset/py.typed
richset-0.4.1.dist-info/LICENSE
richset-0.4.1.dist-info/METADATA
richset-0.4.1.dist-info/WHEEL
richset-0.4.1.dist-info/top_level.txt
richset-0.4.1.dist-info/RECORD
